Workbook

Sheet 測試回報清單
A1: No. | B1: (公會) 回報日期 | C1: (公會) 回報人員 | D1: (公會) 問題說明 (請儘量詳述操作步驟或使用的測試資料, 以利開發人員還原問題除錯) | E1: 特殊活動說明無法移除 | F1: 版本 | G1: 測試帳號 | H1: 狀態 | I1: Priority | J1: 處理人員 | K1: Syscom備註 | L1: Syscom預計調整完成日 | M1: 預計提供 UAT日期 | N1: 實際完成 | O1: 上版日期 | P1: 覆驗/處理/回覆日期 | Q1: 覆驗/處理/回覆人員 | R1: 覆驗/處理/回覆狀況說明 | S1: 公會複驗通過 完成日期 | T1: 備註
A2: =IF(B2="","",ROW(B2)-1) -> 1 | B2: 45139 | C2: 郭副祕 | D2: 這是測試用的訊息 | G2: admin | H2: Cancel | I2: 中
A3: =IF(B3="","",ROW(B3)-1) -> 2 | B3: 45138 | C3: Ariel | D3: 學分計算效能優化 | H3: Close | I3: 中 | J3: Ariel | K3: 已優化完畢，40萬筆資料可正常計算 | O3: 45141
A4: =IF(B4="","",ROW(B4)-1) -> 3 | B4: 45138 | C4: 雙週會 | D4: 活動收據左下角加上經手人章(建課程/活動者) | H4: 覆驗通過 | I4: 中 | J4: Samuel/Brain | T4: 這頁的link無法查詢, 故無法測試
A5: =IF(B5="","",ROW(B5)-1) -> 4 | B5: 45138 | C5: 雙週會 | D5: 活動收據增加印花總繳的浮水印章壓在收執聯字樣附近，此項目僅需全聯會 | H5: Close | I5: 中 | J5: Samuel/Brain
A6: =IF(B6="","",ROW(B6)-1) -> 5 | B6: 45138 | C6: 雙週會 | D6: 因應檔案正確性問題取消地方公會課程直接打到全聯會方式，轉由匯入處理 匯入範例的活動與課程分頁，要加金額欄位(非必填)，若無就是免費，有的話課程結束後讓全聯會/會計師可以印收據 承上，付款日期統一為匯入日期，繳款自動轉為現金，印花稅也以匯入日期算 | H6: Close | I6: 中 | J6: Samuel/Ariel
A7: =IF(B7="","",ROW(B7)-1) -> 6 | B7: 45138 | C7: 雙週會 | D7: 月結事務所在課程結束後學分就可以勾稽，不用等到結清 | H7: Close | I7: 中 | J7: Ariel | K7: 目前只要上完課就會自動勾稽
A8: =IF(B8="","",ROW(B8)-1) -> 7 | B8: 45146 | C8: 教學 | D8: 全聯會執業會員異動的退會改為是學分不足的廢止，狀態中文寫為"廢止(金管會)" 執業登記變更的廢止則是不幹了的那種會計師(不用改) | G8: admin | H8: Close | I8: 中 | J8: Henry | P8: 45219 | R8: 欄位有增加，會計師明細資料欄位有問題，須修正欄位字眼
A9: =IF(B9="","",ROW(B9)-1) -> 8 | B9: 45146 | C9: 教學 | D9: 清單的會籍狀態改為執登狀態 | H9: Close | I9: 中 | J9: Ariel
A10: =IF(B10="","",ROW(B10)-1) -> 9 | B10: 45146 | C10: 黃宜婷 | D10: 非執業會員也需要可以報名上課，有自己的帳號可以繳會費等 | H10: Phase2 | K10: 難度較高為CR
A11: =IF(B11="","",ROW(B11)-1) -> 10 | B11: 45146 | C11: 教學 | D11: 上傳印鑑卡要加註時間日期才能知道什麼時候更新 | H11: Close | I11: 中 | J11: Ariel | P11: 45219 | R11: 將"最後異動日期"修正成登錄日期，日期以最新的為最上層
A12: =IF(B12="","",ROW(B12)-1) -> 11 | B12: 45146 | C12: 教學 | D12: 學分登記表最下方的斷行可以拉回去 1.承辦公開發行公司財務簽證之會計師，每年須進修第四條第一、二款(全聯會專教會講習)14小時，第三~九款合 計26 | H12: Close | I12: 中 | J12: Ariel
A13: =IF(B13="","",ROW(B13)-1) -> 12 | B13: 45146 | C13: 教學 | D13: 預查功能：事務所廢止一年內也要可以被查出來 | H13: Close | I13: 中 | J13: Henry
A14: =IF(B14="","",ROW(B14)-1) -> 13 | B14: 45146 | C14: 教學 | D14: 預查登錄的模組，新增/編輯的"原事務所名稱"改成使用下拉選單(跟事務所管理一樣) | H14: Close | I14: 中 | J14: Henry
A15: =IF(B15="","",ROW(B15)-1) -> 14 | B15: 45155 | C15: 薇伊 | D15: 活動與課程管理中-學員學分編輯查詢-裡面的最後編輯時間要修改成"課程日期(起跟迄)" | H15: Close | I15: 中 | J15: Ariel
A16: =IF(B16="","",ROW(B16)-1) -> 15 | B16: 45155 | C16: 薇伊 | D16: 活動與課程管理中-學分登記表-"會籍"那邊要加一個全部的選項; 拿掉會籍編號的預設數字 | H16: Close | I16: 中 | J16: Ariel
A17: =IF(B17="","",ROW(B17)-1) -> 16 | B17: 45155 | C17: 薇伊 | D17: 會計師持續進修小時登記表-課程日期上加上(民國年) | H17: Close | I17: 中 | J17: Ariel
A18: =IF(B18="","",ROW(B18)-1) -> 17 | B18: 45155 | C18: 薇伊 | D18: "學分匯入"的EXCEL檔: 1.兩個分頁都要增加承辦單位,必填但不要求填入完整全銜. 2.課程那分頁的講師改成非必填. 3.名單頁的報到時間拿掉,由系統取中間值. 4.由此學分匯入的講師,不要進入專教會的講師庫. 5.學分數也要落入檢定範圍. 6.本檔案匯入時,請提供排除重複的防呆警告. 7.檔案匯入後,要跳到學分編輯頁面. | H18: Close | I18: 中 | J18: Ariel
A19: =IF(B19="","",ROW(B19)-1) -> 18 | B19: 45156 | C19: 雙週會 | D19: 活動收據的事務所與會計師文字要對調 改為 OOO 會計師 XXXXXXXX事務所 | H19: Close | I19: 中 | J19: Ariel
A20: =IF(B20="","",ROW(B20)-1) -> 19 | B20: 45156 | C20: 教學 | D20: 全聯會一、二字第來文機關不能自填，影響後面報表，欄位改為可更改 | H20: Close | I20: 中 | J20: Henry
A21: =IF(B21="","",ROW(B21)-1) -> 20 | B21: 45159 | C21: 教學2 | D21: 活動的附件上傳，調整為可以上傳5個檔案，每個限制檔案10MB | H21: Close | I21: 中 | J21: Brian
A22: =IF(B22="","",ROW(B22)-1) -> 21 | B22: 45159 | C22: 教學2 | D22: 前台[我的課程與活動] 顯示的排序邏輯如果開始報名內的排序要調整為活動日期靠近得先排 例如已報名優先，再來是活動日期靠近的 | G22: 活動日期靠近的是在後面，點“即將到來”是靠近的日期在後面，“活動與課程”也一樣 | H22: Close | I22: 低 | J22: Tim | K22: 現在已經可點選近到遠或是遠到近做排序了
A23: =IF(B23="","",ROW(B23)-1) -> 22 | B23: 45159 | C23: 教學2 | D23: 講師模組：新增/編輯除了名字都是非必填 | H23: Close | I23: 中
A24: =IF(B24="","",ROW(B24)-1) -> 23 | B24: 45159 | C24: 教學2 | H24: Close | I24: 中 | J24: Ariel
A25: =IF(B25="","",ROW(B25)-1) -> 24 | B25: 45159 | C25: 教學2 | D25: 優惠券新增時要去抓身份證字號(現在抓成北市會編)，並且要加匯入功能 | H25: Close | I25: 中 | J25: Ariel
A26: =IF(B26="","",ROW(B26)-1) -> 25 | B26: 45159 | C26: 教學2 | H26: 待覆驗 | I26: 中 | J26: Ariel
A27: =IF(B27="","",ROW(B27)-1) -> 26 | B27: 45159 | C27: 教學2 | D27: 優惠券一個年度只能發一次，新增/匯入檢查時發現該年度已經發過要擋掉 | H27: Close | I27: 中 | J27: Ariel
A28: =IF(B28="","",ROW(B28)-1) -> 27 | B28: 45159 | C28: 教學2 | D28: 第一頁學分登記公文的地址要切齊姓名，整體對齊roccpa的r字 9/4目前僅有姓名對齊,地址仍未對齊roccpa的r | H28: Close | I28: 中 | J28: Ariel
A29: =IF(B29="","",ROW(B29)-1) -> 28 | B29: 45159 | C29: 教學2 | D29: 進修時數登記表的查詢介面，要多一個向下排除的勾勾，有的話查詢時就要向下排除地方公會(省公會>...) | H29: Close | I29: 中 | J29: Ariel | K29: 8/24: 查詢介面新增”排除會籍“。 ex: 若會籍勾選“台灣省”，排除會籍勾選"台北市"，需要查出所有台灣省會籍的會員中不包含台北市會籍的會員
A30: =IF(B30="","",ROW(B30)-1) -> 29 | B30: 45159 | C30: 教學2 | D30: 抵用券在報名過程中沒有成功被勾消(會務/會員) -扣法為扣一千&不找零，月結也可以抵 -一次最多只能用一張優惠券 -課堂金額為1000才能使用 | H30: Close | I30: 低 | J30: Ariel
A31: =IF(B31="","",ROW(B31)-1) -> 30 | B31: 45159 | C31: 教學2 | D31: menu要可以直接到助理人員清單內(不鎖事務所) | H31: Close | I31: 中 | J31: Alan
A32: =IF(B32="","",ROW(B32)-1) -> 31 | B32: 45159 | C32: 教學2 | D32: 助理人員清單頁要有身分證字號 | H32: Close | I32: 中 | J32: Alan
A33: =IF(B33="","",ROW(B33)-1) -> 32 | B33: 45159 | C33: 教學2 | D33: 收文要多一個收文型態 有全聯會一字第 二字第 三字第 還有一般的(沒字號)，可參考發文全聯會自第一二三做法 | H33: Close | I33: 低 | J33: Tim
A34: =IF(B34="","",ROW(B34)-1) -> 33 | B34: 45159 | C34: 教學2 | D34: 在助理人員送件的畫面，附件上傳多一個sample可以下載(全聯會提供空白檔) | H34: Close | I34: 中 | J34: Alan
A35: =IF(B35="","",ROW(B35)-1) -> 34 | B35: 45159 | C35: 教學2 | D35: 助理上傳要做檔案大小判定，不可超過perfomance界線 | H35: Close | I35: 中 | J35: Alan
A36: =IF(B36="","",ROW(B36)-1) -> 35 | B36: 45159 | C36: 教學2 | D36: 助理送件的email非必填 | G36: 09/23覆驗為必填選項 | H36: Close | I36: 低 | J36: Alan | K36: 第二審 沒有email 報錯的bug也已修正
A37: =IF(B37="","",ROW(B37)-1) -> 36 | B37: 45159 | C37: 教學2 | D37: 助理公文完要可以指派或是自動指派 | H37: Close | I37: 中 | J37: Alan
A38: =IF(B38="","",ROW(B38)-1) -> 37 | B38: 45159 | C38: 林香如 | D38: 優惠券要能設定期限 | H38: Phase2
A39: =IF(B39="","",ROW(B39)-1) -> 38 | B39: 45162 | C39: 省公會黃總幹事 | D39: 全聯會要有功能可以查詢各會計師加入地方公會的數字 例如加入北市 XX人，加入北市與省公會XX人... | H39: Phase2
A40: =IF(B40="","",ROW(B40)-1) -> 39 | B40: 45162 | C40: 郭副祕 | D40: 公文簽收表調整匹配全聯會 | H40: Phase2
A41: =IF(B41="","",ROW(B41)-1) -> 40 | B41: 45162 | C41: 葉憶婷 | D41: 會員管理頁面要加一個「執業登記狀態」的篩選器 | H41: Close | I41: 中 | J41: Brian
A42: =IF(B42="","",ROW(B42)-1) -> 41 | B42: 45162 | C42: 葉憶婷 | D42: 會員資料管理>會員異動，異動中的許多變更欄位，異動紀錄的明細要顯示出來(公文日期與項目) | H42: Close | I42: 中 | J42: Ariel
A43: =IF(B43="","",ROW(B43)-1) -> 42 | B43: 45162 | C43: 葉憶婷 | D43: 會員資料管理>會員異動，懲戒的起訖日期不用必填 | H43: Close | I43: 中 | J43: Brian
A44: =IF(B44="","",ROW(B44)-1) -> 43 | B44: 45162 | C44: 葉憶婷 | D44: 事務所異動>主分所互換轉換要有新舊所的名稱可以填寫 | H44: Close | I44: 中 | J44: Alan
A45: =IF(B45="","",ROW(B45)-1) -> 44 | B45: 45162 | C45: 葉憶婷 | D45: 會員角色登入看的會員資料頁面：會籍資料(改為北市編號移到下方的臺省編號旁邊)、會計師統編(移除)、出生地&籍貫(移除)、入會日期(更名為執業登記日期)、入會發文號(更名為執業登記文號)、退會日期(移除)、註銷(死亡)會籍日期(不需要)、廢止註銷日期旁邊的公會收文號(改為廢止收文號)、發布機關&公文日期&公文字號&發給會員證書日期&會員證書字號(移除)、停權標註&停權日期&復權日期(移除)、不收費日期&恢復收費日期(移除)、住宅地址(移除)、區號&住宅電話等(移除)、Email刊登到不收會費(移除)、中華稅協&稅協代理人證書等欄位(移除) | H45: Close | I45: 中 | J45: Brian
A46: =IF(B46="","",ROW(B46)-1) -> 45 | B46: 45162 | C46: 黃宜婷 | D46: 非執業會員明細 會計師統編(移除)、頒發日期右邊的欄位(標題要寫為會計師考試及格證書字號)、奉准日期右邊的欄位(標題要寫會計師證書字號)、下方的會計師考試及格證書字號(直接移除)、通訊地址新增一個勾選(同戶籍地) | H46: Close | I46: 中 | J46: Alan
A47: =IF(B47="","",ROW(B47)-1) -> 46 | B47: 45162 | C47: 黃宜婷 | D47: 助理人員送件 會計師資格、兩以上工作服務證書、記帳士證書，都先預設為否 | H47: Close | I47: 中 | J47: Alan
A48: =IF(B48="","",ROW(B48)-1) -> 47 | B48: 45162 | C48: 黃宜婷 | D48: 助理人員送件 打身份證字號時，若已存在於本事務所，狀態預設填離職，若否則為到職 | H48: Close | I48: 中 | J48: Alan
A49: =IF(B49="","",ROW(B49)-1) -> 48 | B49: 45162 | C49: 黃宜婷 | D49: 助理人員審核 若有上傳成績，該員姓名紅字加粗 | H49: Cancel
A50: =IF(B50="","",ROW(B50)-1) -> 49 | B50: 45162 | C50: 黃宜婷 | D50: 助理人員審核 多一個第二關審核按鈕，在第一個審核按完後才出現 ※加一個function是第二關審核 | H50: Close | I50: 中 | J50: Alan
A51: =IF(B51="","",ROW(B51)-1) -> 50 | B51: 45162 | C51: 黃宜婷 | D51: 助理送件的生日改為民國年 | E51: 選單的民國年可以用打的嗎? 點選99年份，秀出來的民國年只看到的9看不到後面的確切的出生年 | H51: Close | I51: 中 | J51: Alan
A52: =IF(B52="","",ROW(B52)-1) -> 51 | B52: 45162 | C52: 黃宜婷 | D52: 助理人員送件 請在保存的按鈕旁邊 粗體黑字顯示：請於保存後，將異動表第二聯郵寄至全聯會備查 | H52: Close | I52: 中 | J52: Alan
A53: =IF(B53="","",ROW(B53)-1) -> 52 | B53: 45162 | C53: 林香如 | D53: 後續增加活動模板複製功能 | H53: Phase2
A54: =IF(B54="","",ROW(B54)-1) -> 53 | B54: 45162 | C54: 林香如 | D54: 活動課程建立聯絡人與Email改為非必填 | H54: Close | I54: 中 | J54: Ariel
A55: =IF(B55="","",ROW(B55)-1) -> 54 | B55: 45162 | C55: 林香如 | D55: 活動課程建立 到下方活動的時候名稱自動帶主標，時間自動帶活動日期 | H55: Close | I55: 中 | J55: Ariel
A56: =IF(B56="","",ROW(B56)-1) -> 55 | B56: 45162 | C56: 林香如 | D56: 活動課程開始前會員/用戶12小時就要不能取消 但後台要可以按取消 | H56: Close | I56: 中 | J56: Ariel
A57: =IF(B57="","",ROW(B57)-1) -> 56 | B57: 45166 | C57: 邱薇伊 | D57: 課程與活動加一個學分送件功能 會計師/事務所可自行進入填寫表單送件 後台匯出即為可匯入活動之格式 後台需要有標籤可以標註是否處理完畢此項申請 | H57: Phase2
A58: =IF(B58="","",ROW(B58)-1) -> 57 | B58: 45166 | C58: 葉憶婷 | D58: 會計師資料按編輯戶籍地址應該要不可更動 | H58: Close | I58: 中 | J58: Ariel
A59: =IF(B59="","",ROW(B59)-1) -> 58 | B59: 45166 | C59: 葉憶婷 | D59: 會計師資料欄位要有電話欄位 | H59: Close | I59: 中 | J59: Ariel
A60: =IF(B60="","",ROW(B60)-1) -> 59 | B60: 45166 | C60: 葉憶婷 | D60: 事務所資料>編輯的電話欄位要可以修改，現在是灰的 | H60: Close | I60: 中 | J60: Alan
A61: =IF(B61="","",ROW(B61)-1) -> 60 | B61: 45166 | C61: 葉憶婷 | D61: 會員查詢>匯出 缺：主事務所相關資訊、執登日期、執登文號、三區域執業登記相關資訊、各地方入會日期、各地方會籍編號(北-會籍編號、北-入會日期...) | H61: Close | I61: 中 | J61: Alan | R61: 欄位擺放需做調整
A62: =IF(B62="","",ROW(B62)-1) -> 61 | B62: 45166 | C62: 葉憶婷 | D62: 新增/編輯會員資料，要可以增修地方公會會籍編號/入會日期的欄位 | H62: Close | I62: 低 | J62: Alan
A63: =IF(B63="","",ROW(B63)-1) -> 62 | B63: 45166 | C63: 林香如 | D63: 事務所月結 鼎碩事務所8月份無法按結清，收據pdf也會錯誤 | H63: Close | I63: 中 | J63: Alan
A64: =IF(B64="","",ROW(B64)-1) -> 63 | B64: 45166 | C64: 林香如 | D64: 事務所月結 哇哈哈事務所月份查詢 - 2023/6/1-2023/7/31還是會出現八月份資料 | H64: Close | I64: 中 | J64: Alan
A65: =IF(B65="","",ROW(B65)-1) -> 64 | B65: 45166 | C65: 林香如 | D65: 事務所月結 匯出的Excel要有課程日期、title、事務所與報名者的資料、抵用券序號 | H65: Close | I65: 中 | J65: Alan
A66: =IF(B66="","",ROW(B66)-1) -> 65 | B66: 45166 | C66: 林香如 | D66: 課程活動 再繳費的頁面多提醒，「請於30分鐘內完成繳費，逾期將取消報名」 | H66: Close | I66: 中 | J66: Brian
A67: =IF(B67="","",ROW(B67)-1) -> 66 | B67: 45167 | C67: 邱薇伊 | D67: 報表模組-洗錢不足報表-四公會那個欄位,是要產出會籍號碼; 增加4條2的欄位(洗防時數的規定是只要4條1.5.8款有3小時屬洗錢防制的就符合,但實務上若4條2有洗錢時數也會列入) | H67: Close | I67: 中 | J67: Ariel
A68: =IF(B68="","",ROW(B68)-1) -> 67 | B68: 45167 | C68: 邱薇伊 | D68: 報表模組-持續進修不足報表-四公會那個欄位,是要產出會籍號碼; | H68: Close | I68: 中 | J68: Ariel
A69: =IF(B69="","",ROW(B69)-1) -> 68 | B69: 45167 | C69: 邱薇伊 | D69: 報表模組-進修資料明細-起始日及結束日欄位格式請改為" x月x日",如當初提供之報表範本格式 | H69: Close | I69: 中 | J69: Tim
A70: =IF(B70="","",ROW(B70)-1) -> 69 | B70: 45167 | C70: 邱薇伊 | D70: 上面回報序號NO16 會計師持續進修小時登記表-課程日期上加上(民國年) **日期可以改加在日期前面,而不是課程主題前面嗎? | H70: Close | I70: 中 | J70: Ariel
A71: =IF(B71="","",ROW(B71)-1) -> 70 | B71: 45173 | C71: 林香如 | D71: 活動新增時間要可以產出兩種QR code便於報到 即上下午的課程可以分開報到與分開拿學分 | H71: Phase2
A72: =IF(B72="","",ROW(B72)-1) -> 71 | B72: 45173 | C72: 邱薇伊 | D72: 會員可以查自己的學分登記表(查詢介面要可以選年度) | H72: Close | I72: 中 | J72: Ariel
A73: =IF(B73="","",ROW(B73)-1) -> 72 | B73: 45173 | C73: 邱薇伊 | D73: 建課程時的課程年度 預設為本年度，但下拉選單可以選到本年度+1 | H73: Close | I73: 低 | J73: Tim
A74: =IF(B74="","",ROW(B74)-1) -> 73 | B74: 45166 | C74: 林香如 | D74: 建立課程時，系列課程的下拉清單藥可以搜尋，也需要一併檢查是否有撈出全部資料 12/25: 目前清單中的都只能單選，沒辦法一次多選要的課程報名(反覆報名須考慮重複排除問題) | H74: 覆驗失敗 | I74: 低 | J74: Ariel
A75: =IF(B75="","",ROW(B75)-1) -> 74 | B75: 45177 | C75: 邱薇伊 | D75: 報表模組-持續進修不足報表: 1.電話的欄位出現手機號碼,手機欄出現e-mail;正常是電話(事務所的),手機跟mail三種資料都要產出ok. 2."廢止"欄位對應的資料應為執業登記核准的狀態;"公開"的欄位要對應公開發行財務簽證的狀態. 3.像如果產出111年未達的報表時,裡面的第19.20筆"王阿明123" 他系統資料是設定有核准公開發行簽證,但這邊的"公開"並未對應.像第3.4筆的劉燈發(張振土) ,他執業登記是核准的,但他這邊廢止欄位卻顯示y. | E75: 1."時數標準"條件若選擇"未達"跑出來的報表是空白的.選擇"全部"跟"已達"跑出來的筆數是一樣的 2.執業登記跟公發狀態還是沒有對應,如111年的張宗銘 | H75: Close | I75: 低 | J75: Ariel
A76: =IF(B76="","",ROW(B76)-1) -> 75 | B76: 45177 | C76: 邱薇伊 | D76: 課程活動報名管理-"類型"的地方是否能有篩選功能或分類功能,不然一但所有會員的事務所自辦或其他資料都進去後,很快就破千筆或上萬筆,根本找不到自己要的課程 | H76: Close
A77: =IF(B77="","",ROW(B77)-1) -> 76 | B77: 45177 | C77: 邱薇伊 | D77: 學分匯入的設定,不同日期,同一課程名稱被判斷重複課程(講師跟學員都要在測試) | H77: Close | J77: Samuel | K77: 這一題驗過沒有問題
A78: =IF(B78="","",ROW(B78)-1) -> 77 | B78: 45177 | C78: 邱薇伊 | D78: 學分清單的警示小圖示, 要以上年度的學分為範圍, 例: 今年為112年, 查詢111年學分不足與洗防法不足來顯示 | H78: Close | I78: 中 | J78: Ariel
A79: =IF(B79="","",ROW(B79)-1) -> 78 | B79: 45177 | C79: 邱薇伊 | D79: 匯入的講師,沒有依講師學分給較高的學分數 | H79: Close | I79: 中 | J79: Ariel
A80: =IF(B80="","",ROW(B80)-1) -> 79 | B80: 45179 | C80: 郭馨怡 | D80: 有優惠券的會計師沒有出現使用優惠券的選項，而是出現月結的選項 | E80: 有優惠券的會計師已可選擇優惠券，但其非月結事務所，點送出報名後仍有月結的選項 | H80: Close | I80: 中 | J80: Brian
A81: =IF(B81="","",ROW(B81)-1) -> 80 | B81: 45179 | C81: 林香如 | D81: 不能新增優惠券 | H81: Close | I81: 中 | J81: Sameul | K81: 測試加入陳志光優惠卷, 確實可以加入
A82: =IF(B82="","",ROW(B82)-1) -> 81 | B82: 45179 | C82: 林香如 | D82: 課程結束，沒有任何印收據.學分的選項或按鈕 | H82: Close | I82: 中 | J82: Samuel | K82: 以陳志光為例, 以本人身份登入, 在課程活動報名管理>活動與課程>選擇"ESG報導現況及公司治理評鑑之ESG(2)"會出現"活動收據"圖示 及 "列印學分證明" 按鈕
A83: =IF(B83="","",ROW(B83)-1) -> 82 | B83: 45179 | C83: 石淯伶 | D83: 課程結束後，填寫問題問卷回饋出現錯誤訊息 用會計師帳號>我的活動>填寫問卷按送出後出現「EVENT NOT FOUND」的錯誤訊息 全聯會：P123350417 | H83: Close | I83: 低 | J83: Peter | O83: 45341
A84: =IF(B84="","",ROW(B84)-1) -> 83 | B84: 45179 | C84: 林香如 | D84: 個人活動頁面排序無效. | H84: Close | I84: 中 | J84: Tim
A85: =IF(B85="","",ROW(B85)-1) -> 84 | B85: 45180 | C85: 林香如 | D85: 非本人報到, 狀態要為報到成功, 不退費, 不算學分, 並提供備註欄, 供記錄是某位人員報到 | H85: Phase2 | K85: 已緊急加上備註, 讓系統未來可以在資料庫中查出,至於後面其它功能, 是要在哪查詢, 有待討論
A86: =IF(B86="","",ROW(B86)-1) -> 85 | B86: 45180 | C86: 林香如 | D86: 講師(專教會學分類別為4條2)系統請直接提供 2023/9/20 課程與活動經發布且結束後, 自動把學分分配給該會計師, (4條1才適用) | H86: Close | I86: 中 | J86: Ariel
A87: =IF(B87="","",ROW(B87)-1) -> 86 | B87: 45180 | C87: 林香如 | D87: 如何幫學員印出學分證明 | H87: Close | I87: 低 | J87: Samuel | K87: 在課程結束後,於"統計分析",有報名的學員, 動作, 有一按鈕 "學生證明" 可使用
A88: =IF(B88="","",ROW(B88)-1) -> 87 | B88: 45180 | C88: 林香如 | D88: 印花稅以金額為Group, 相同金額且序號一致的請列入同一列, 並列出序號,張數,金額,小計, 並於最後出現總計-目前列出的印花稅總表看不出來是否有按照順序，可否拿111年的舊資料來測試否則看不出來設定的邏輯 | H88: 覆驗通過 | I88: 低 | J88: Ariel | K88: 這部份系統已有處理
A89: =IF(B89="","",ROW(B89)-1) -> 88 | B89: 45180 | C89: 葉憶婷 | D89: 印鑑卡,請直接歸入全聯會, 印鑑卡旁之日期為, 申請的異動(新增) 的異動日期, 而非目前顯示的最後異動時間 | H89: Close | I89: 中 | J89: Tim
A90: =IF(B90="","",ROW(B90)-1) -> 89 | B90: 45180 | C90: 葉憶婷 | D90: 報到時所顯示的印鑑卡應為最新的印鑑卡-目前的方式還看不出來是否為最新的印鑑卡 | H90: Close | I90: 中 | J90: Tim
A91: =IF(B91="","",ROW(B91)-1) -> 90 | B91: 45180 | C91: 林香如 | D91: 活動與課程目前測試已上百列資訊, 增加在活動與課程以關鍵字查詢的功能 | H91: Close | I91: 低 | J91: Brian
A92: =IF(B92="","",ROW(B92)-1) -> 91 | B92: 45180 | C92: 葉憶婷 | D92: 各型態事務所家數, 請用主事務所來計算 | H92: Close | I92: 中 | J92: Brian
A93: =IF(B93="","",ROW(B93)-1) -> 92 | B93: 45180 | C93: 邱薇伊 | D93: 學分編輯的編號改為身分證 | H93: Close | I93: 中 | J93: Brian | K93: 功能已存在, 尚需把編號改為身分證
A94: =IF(B94="","",ROW(B94)-1) -> 93 | B94: 45180 | C94: 邱薇伊 | D94: 洗防的學分在舊系統均以"洗錢"關鍵字顯示於課程名稱中, 請區分並實現於新系統中 | H94: Close | I94: 中 | J94: Tim
A95: =IF(B95="","",ROW(B95)-1) -> 94 | B95: 45180 | C95: 邱薇伊 | D95: 1)進修時數登記表列印, 請加上, 通知(搭配公文的檔案) | H95: Close | I95: 中 | J95: Ariel
A96: =IF(B96="","",ROW(B96)-1) -> 95 | B96: 45182 | C96: 林香如 | D96: 學分證明列印-課程日期的"日"不見了，名稱最多只到15個字後面就不見了，頁面這麼大能否不要限制字數讓他自動換行?理事長章可以往上移一點?版面比較好看 | E96: 沒有列印證明的按鈕 | H96: Close | I96: 中 | J96: Ariel
A97: =IF(B97="","",ROW(B97)-1) -> 96 | B97: 45182 | C97: 邱薇伊 | D97: 學分登記表裡面的"應補時數"欄位,若是已超過建議時數的部分是否用負數呈現 . 或是能在討論如何配合非專教會欄位調整計算方式. 報表模組-"年度學分數明細"也要配合更改調整 | H97: Close | I97: 中 | J97: Ariel
A98: =IF(B98="","",ROW(B98)-1) -> 97 | B98: 45182 | C98: 陳志光反應 | D98: 在APP STORE搜尋會計師公會，出來的是全聯會舊的APP是否可協助移除?或是更改? | H98: Cancel | K98: 這要請KPMG下架
A99: =IF(B99="","",ROW(B99)-1) -> 98 | B99: 45183 | C99: 黃宜婷 | D99: 全聯會收文及一二三字第，收文碼應為8位數號碼。 | H99: Close | I99: 低 | J99: Brian
A100: =IF(B100="","",ROW(B100)-1) -> 99 | B100: 45187 | C100: 邱薇伊 | D100: 在學分登記表裡的table 呈現, 數字0 -> 空白 | H100: Close | I100: 低
...

Sheet 定義
A1: Bug分級定義 | F1: 總Bug數量 | G1: 待修正/處理中/覆驗失敗 | H1: 待覆驗 | I1: Close/Cancel/覆驗通過
A2: Critial | B2: 嚴重影響產品使用，系統支援問題，安全性問題 | F2: 最高 | G2: =countifs('測試回報清單'!$I:$I,$F2,'測試回報清單'!$H:$H,"待修正")+countifs('測試回報清單'!$I:$I,$F2,'測試回報清單'!$H:$H,"處理中")+countifs('測試回報清單'!$I:$I,$F2,'測試回報清單'!$H:$H,"覆驗失敗") -> 0 | H2: =countifs('測試回報清單'!$I:$I,$F2,'測試回報清單'!$H:$H,"待覆驗") -> 0 | I2: =countifs('測試回報清單'!$I:$I,$F2,'測試回報清單'!$H:$H,"Close")+countifs('測試回報清單'!$I:$I,$F2,'測試回報清單'!$H:$H,"Cancel")+countifs('測試回報清單'!$I:$I,$F2,'測試回報清單'!$H:$H,"覆驗通過") -> 0
A3: High | B3: 功能不符合流程且不能往下執行，且有效能問題 | F3: 高 | G3: =countifs('測試回報清單'!$I:$I,$F3,'測試回報清單'!$H:$H,"待修正")+countifs('測試回報清單'!$I:$I,$F3,'測試回報清單'!$H:$H,"處理中")+countifs('測試回報清單'!$I:$I,$F3,'測試回報清單'!$H:$H,"覆驗失敗") -> 0 | H3: =countifs('測試回報清單'!$I:$I,$F3,'測試回報清單'!$H:$H,"待覆驗") -> 1 | I3: =countifs('測試回報清單'!$I:$I,$F3,'測試回報清單'!$H:$H,"Close")+countifs('測試回報清單'!$I:$I,$F3,'測試回報清單'!$H:$H,"Cancel")+countifs('測試回報清單'!$I:$I,$F3,'測試回報清單'!$H:$H,"覆驗通過") -> 1
A4: Mid | B4: 不影響主流程, 但功能錯誤, 或缺少必要欄位 | F4: 中 | G4: =countifs('測試回報清單'!$I:$I,$F4,'測試回報清單'!$H:$H,"待修正")+countifs('測試回報清單'!$I:$I,$F4,'測試回報清單'!$H:$H,"處理中")+countifs('測試回報清單'!$I:$I,$F4,'測試回報清單'!$H:$H,"覆驗失敗") -> 0 | H4: =countifs('測試回報清單'!$I:$I,$F4,'測試回報清單'!$H:$H,"待覆驗") -> 3 | I4: =countifs('測試回報清單'!$I:$I,$F4,'測試回報清單'!$H:$H,"Close")+countifs('測試回報清單'!$I:$I,$F4,'測試回報清單'!$H:$H,"Cancel")+countifs('測試回報清單'!$I:$I,$F4,'測試回報清單'!$H:$H,"覆驗通過") -> 93
A5: Low | B5: 一些UI/Wording問題，不影響功能 | F5: 低 | G5: =countifs('測試回報清單'!$I:$I,$F5,'測試回報清單'!$H:$H,"待修正")+countifs('測試回報清單'!$I:$I,$F5,'測試回報清單'!$H:$H,"處理中")+countifs('測試回報清單'!$I:$I,$F5,'測試回報清單'!$H:$H,"覆驗失敗") -> 4 | H5: =countifs('測試回報清單'!$I:$I,$F5,'測試回報清單'!$H:$H,"待覆驗") -> 7 | I5: =countifs('測試回報清單'!$I:$I,$F5,'測試回報清單'!$H:$H,"Close")+countifs('測試回報清單'!$I:$I,$F5,'測試回報清單'!$H:$H,"Cancel")+countifs('測試回報清單'!$I:$I,$F5,'測試回報清單'!$H:$H,"覆驗通過") -> 129
F9: Bug數量(10/23之前) | G9: 待修正/處理中/覆驗失敗 | H9: 待覆驗 | I9: Close/Cancel/覆驗通過
F10: 最高 | G10: =countifs('測試回報清單'!$I:$I,$F10,'測試回報清單'!$H:$H,"待修正",'測試回報清單'!B:B,"<"&"2023/10/23")+countifs('測試回報清單'!$I:$I,$F10,'測試回報清單'!$H:$H,"處理中",'測試回報清單'!B:B,"<"&"2023/10/23")+countifs('測試回報清單'!$I:$I,$F10,'測試回報清單'!$H:$H,"覆驗失敗",'測試回報清單'!B:B,"<"&"2023/10/23") -> 0 | H10: =countifs('測試回報清單'!$I:$I,$F10,'測試回報清單'!$H:$H,"待覆驗",'測試回報清單'!B:B,"<"&"2023/10/23") -> 0 | I10: =countifs('測試回報清單'!$I:$I,$F10,'測試回報清單'!$H:$H,"Close",'測試回報清單'!B:B,"<"&"2023/10/23")+countifs('測試回報清單'!$I:$I,$F10,'測試回報清單'!$H:$H,"Cancel",'測試回報清單'!B:B,"<"&"2023/10/23")+countifs('測試回報清單'!$I:$I,$F10,'測試回報清單'!$H:$H,"覆驗通過",'測試回報清單'!B:B,"<"&"2023/10/23") -> 0
F11: 高 | G11: =countifs('測試回報清單'!$I:$I,$F11,'測試回報清單'!$H:$H,"待修正",'測試回報清單'!B:B,"<"&"2023/10/23")+countifs('測試回報清單'!$I:$I,$F11,'測試回報清單'!$H:$H,"處理中",'測試回報清單'!B:B,"<"&"2023/10/23")+countifs('測試回報清單'!$I:$I,$F11,'測試回報清單'!$H:$H,"覆驗失敗",'測試回報清單'!B:B,"<"&"2023/10/23") -> 0 | H11: =countifs('測試回報清單'!$I:$I,$F11,'測試回報清單'!$H:$H,"待覆驗",'測試回報清單'!B:B,"<"&"2023/10/23") -> 0 | I11: =countifs('測試回報清單'!$I:$I,$F11,'測試回報清單'!$H:$H,"Close",'測試回報清單'!B:B,"<"&"2023/10/23")+countifs('測試回報清單'!$I:$I,$F11,'測試回報清單'!$H:$H,"Cancel",'測試回報清單'!B:B,"<"&"2023/10/23")+countifs('測試回報清單'!$I:$I,$F11,'測試回報清單'!$H:$H,"覆驗通過",'測試回報清單'!B:B,"<"&"2023/10/23") -> 0
F12: 中 | G12: =countifs('測試回報清單'!$I:$I,$F12,'測試回報清單'!$H:$H,"待修正",'測試回報清單'!B:B,"<"&"2023/10/23")+countifs('測試回報清單'!$I:$I,$F12,'測試回報清單'!$H:$H,"處理中",'測試回報清單'!B:B,"<"&"2023/10/23")+countifs('測試回報清單'!$I:$I,$F12,'測試回報清單'!$H:$H,"覆驗失敗",'測試回報清單'!B:B,"<"&"2023/10/23") -> 0 | H12: =countifs('測試回報清單'!$I:$I,$F12,'測試回報清單'!$H:$H,"待覆驗",'測試回報清單'!B:B,"<"&"2023/10/23") -> 2 | I12: =countifs('測試回報清單'!$I:$I,$F12,'測試回報清單'!$H:$H,"Close",'測試回報清單'!B:B,"<"&"2023/10/23")+countifs('測試回報清單'!$I:$I,$F12,'測試回報清單'!$H:$H,"Cancel",'測試回報清單'!B:B,"<"&"2023/10/23")+countifs('測試回報清單'!$I:$I,$F12,'測試回報清單'!$H:$H,"覆驗通過",'測試回報清單'!B:B,"<"&"2023/10/23") -> 88
F13: 低 | G13: =countifs('測試回報清單'!$I:$I,$F13,'測試回報清單'!$H:$H,"待修正",'測試回報清單'!B:B,"<"&"2023/10/23")+countifs('測試回報清單'!$I:$I,$F13,'測試回報清單'!$H:$H,"處理中",'測試回報清單'!B:B,"<"&"2023/10/23")+countifs('測試回報清單'!$I:$I,$F13,'測試回報清單'!$H:$H,"覆驗失敗",'測試回報清單'!B:B,"<"&"2023/10/23") -> 1 | H13: =countifs('測試回報清單'!$I:$I,$F13,'測試回報清單'!$H:$H,"待覆驗",'測試回報清單'!B:B,"<"&"2023/10/23") -> 1 | I13: =countifs('測試回報清單'!$I:$I,$F13,'測試回報清單'!$H:$H,"Close",'測試回報清單'!B:B,"<"&"2023/10/23")+countifs('測試回報清單'!$I:$I,$F13,'測試回報清單'!$H:$H,"Cancel",'測試回報清單'!B:B,"<"&"2023/10/23")+countifs('測試回報清單'!$I:$I,$F13,'測試回報清單'!$H:$H,"覆驗通過",'測試回報清單'!B:B,"<"&"2023/10/23") -> 59

Sheet 測試注意事項
A1: 1.會籍管理新增會員及使用者管理新增帳號時，請填寫測試者自己的email，以便接收密碼信。
A2: 2.印鑑證明申請使用測試線上支付繳款時，請使用line pay掃描後，選擇取消付款即可測試繳款成功。
